{
  "version": 1,
  "generated_at": "2026-06-04T08:01:05-07:00",
  "plugins": [
    {
      "id": "net.mallard.discworld-autocols",
      "name": "Discworld Autocols",
      "description": "",
      "language": "lua",
      "homepage": "https://github.com/wizardquack/mallardx-discworld-autocols",
      "tags": [
        "discworld"
      ],
      "worlds_match": [
        "discworld.starturtle.net:*"
      ],
      "versions": [
        {
          "version": "0.2.0",
          "published_at": "2026-06-04T15:03:55.833Z",
          "archive_url": "https://mallard-marketplace.vnsf.xyz/archives/net.mallard.discworld-autocols/0.2.0/discworld-autocols.mallardx",
          "archive_sha256": "34ce6f4cbf18bdbc93c256da3de20438b1868fc646551ba00f7643267950346e",
          "signature_url": "https://mallard-marketplace.vnsf.xyz/archives/net.mallard.discworld-autocols/0.2.0/discworld-autocols.mallardx.minisig",
          "manifest_url": "https://mallard-marketplace.vnsf.xyz/archives/net.mallard.discworld-autocols/0.2.0/plugin.toml",
          "minimum_app_version": "0.0.1",
          "permissions_summary": {
            "sends": true,
            "gmcp_access": [],
            "notifications": false,
            "keychain": false,
            "network": [],
            "filesystem": [],
            "clipboard": "none",
            "external_app": []
          },
          "withdrawn": false,
          "withdrawn_reason": null
        },
        {
          "version": "0.1.3",
          "published_at": "2026-06-04T15:03:56.816Z",
          "archive_url": "https://mallard-marketplace.vnsf.xyz/archives/net.mallard.discworld-autocols/0.1.3/discworld-autocols.mallardx",
          "archive_sha256": "19d5e13d2dea82bad112582bc73674376d29af3ae495499967a40e1ca076f11d",
          "signature_url": "https://mallard-marketplace.vnsf.xyz/archives/net.mallard.discworld-autocols/0.1.3/discworld-autocols.mallardx.minisig",
          "manifest_url": "https://mallard-marketplace.vnsf.xyz/archives/net.mallard.discworld-autocols/0.1.3/plugin.toml",
          "minimum_app_version": "0.0.1",
          "permissions_summary": {
            "sends": true,
            "gmcp_access": [],
            "notifications": false,
            "keychain": false,
            "network": [],
            "filesystem": [],
            "clipboard": "none",
            "external_app": []
          },
          "withdrawn": false,
          "withdrawn_reason": null
        },
        {
          "version": "0.1.2",
          "published_at": "2026-06-04T15:03:55.332Z",
          "archive_url": "https://mallard-marketplace.vnsf.xyz/archives/net.mallard.discworld-autocols/0.1.2/discworld-autocols.mallardx",
          "archive_sha256": "22e6efec8a66fd6a545eba7fc3b0fbc74a78baa0db726a703054945ae9f46384",
          "signature_url": "https://mallard-marketplace.vnsf.xyz/archives/net.mallard.discworld-autocols/0.1.2/discworld-autocols.mallardx.minisig",
          "manifest_url": "https://mallard-marketplace.vnsf.xyz/archives/net.mallard.discworld-autocols/0.1.2/plugin.toml",
          "minimum_app_version": "0.0.1",
          "permissions_summary": {
            "sends": true,
            "gmcp_access": [],
            "notifications": false,
            "keychain": false,
            "network": [],
            "filesystem": [],
            "clipboard": "none",
            "external_app": []
          },
          "withdrawn": false,
          "withdrawn_reason": null
        },
        {
          "version": "0.1.1",
          "published_at": "2026-06-04T15:03:56.317Z",
          "archive_url": "https://mallard-marketplace.vnsf.xyz/archives/net.mallard.discworld-autocols/0.1.1/discworld-autocols.mallardx",
          "archive_sha256": "96a295d0dc8cb0f893860d20cc5b58bd40ddb160c2c3564a7eed1ddd5f417caf",
          "signature_url": "https://mallard-marketplace.vnsf.xyz/archives/net.mallard.discworld-autocols/0.1.1/discworld-autocols.mallardx.minisig",
          "manifest_url": "https://mallard-marketplace.vnsf.xyz/archives/net.mallard.discworld-autocols/0.1.1/plugin.toml",
          "minimum_app_version": "0.0.1",
          "permissions_summary": {
            "sends": true,
            "gmcp_access": [],
            "notifications": false,
            "keychain": false,
            "network": [],
            "filesystem": [],
            "clipboard": "none",
            "external_app": []
          },
          "withdrawn": false,
          "withdrawn_reason": null
        }
      ]
    },
    {
      "id": "net.mallard.discworld-chat",
      "name": "Discworld Chat",
      "description": "",
      "language": "lua",
      "homepage": "https://github.com/wizardquack/mallardx-discworld-chat",
      "tags": [
        "discworld",
        "panel",
        "chat"
      ],
      "worlds_match": [
        "discworld.starturtle.net:*"
      ],
      "versions": [
        {
          "version": "0.1.1",
          "published_at": "2026-06-04T15:04:02.773Z",
          "archive_url": "https://mallard-marketplace.vnsf.xyz/archives/net.mallard.discworld-chat/0.1.1/discworld-chat.mallardx",
          "archive_sha256": "96569ad8379572abb4c00d76e08fb835adb66e424ce724931e187bccbe3424dd",
          "signature_url": "https://mallard-marketplace.vnsf.xyz/archives/net.mallard.discworld-chat/0.1.1/discworld-chat.mallardx.minisig",
          "manifest_url": "https://mallard-marketplace.vnsf.xyz/archives/net.mallard.discworld-chat/0.1.1/plugin.toml",
          "minimum_app_version": "0.0.1",
          "permissions_summary": {
            "sends": false,
            "gmcp_access": [],
            "notifications": false,
            "keychain": false,
            "network": [],
            "filesystem": [],
            "clipboard": "none",
            "external_app": []
          },
          "withdrawn": false,
          "withdrawn_reason": null
        },
        {
          "version": "0.1.0",
          "published_at": "2026-06-04T15:04:02.148Z",
          "archive_url": "https://mallard-marketplace.vnsf.xyz/archives/net.mallard.discworld-chat/0.1.0/discworld-chat.mallardx",
          "archive_sha256": "8d420705d76f4159993d06cf1e9d508c8460388969f3524306f901a2b6eb491a",
          "signature_url": "https://mallard-marketplace.vnsf.xyz/archives/net.mallard.discworld-chat/0.1.0/discworld-chat.mallardx.minisig",
          "manifest_url": "https://mallard-marketplace.vnsf.xyz/archives/net.mallard.discworld-chat/0.1.0/plugin.toml",
          "minimum_app_version": "0.0.1",
          "permissions_summary": {
            "sends": false,
            "gmcp_access": [],
            "notifications": false,
            "keychain": false,
            "network": [],
            "filesystem": [],
            "clipboard": "none",
            "external_app": []
          },
          "withdrawn": false,
          "withdrawn_reason": null
        }
      ]
    },
    {
      "id": "net.mallard.discworld-grouping",
      "name": "Discworld Grouping",
      "description": "",
      "language": "lua",
      "homepage": "https://github.com/wizardquack/mallardx-discworld-grouping",
      "tags": [
        "discworld",
        "panel",
        "group"
      ],
      "worlds_match": [
        "discworld.starturtle.net:*"
      ],
      "versions": [
        {
          "version": "0.1.1",
          "published_at": "2026-06-04T15:03:59.952Z",
          "archive_url": "https://mallard-marketplace.vnsf.xyz/archives/net.mallard.discworld-grouping/0.1.1/discworld-grouping.mallardx",
          "archive_sha256": "9152ffd7951eb8e93ea431c637e4080c89564fe1e95412af9007698473015c29",
          "signature_url": "https://mallard-marketplace.vnsf.xyz/archives/net.mallard.discworld-grouping/0.1.1/discworld-grouping.mallardx.minisig",
          "manifest_url": "https://mallard-marketplace.vnsf.xyz/archives/net.mallard.discworld-grouping/0.1.1/plugin.toml",
          "minimum_app_version": "0.0.1",
          "permissions_summary": {
            "sends": true,
            "gmcp_access": [],
            "notifications": false,
            "keychain": false,
            "network": [],
            "filesystem": [],
            "clipboard": "none",
            "external_app": []
          },
          "withdrawn": false,
          "withdrawn_reason": null
        },
        {
          "version": "0.1.0",
          "published_at": "2026-06-04T15:03:59.448Z",
          "archive_url": "https://mallard-marketplace.vnsf.xyz/archives/net.mallard.discworld-grouping/0.1.0/discworld-grouping.mallardx",
          "archive_sha256": "887025cdd7c560a23d7fd64e54b3abbc5006fae32f7d7f6be754e418ff3dce96",
          "signature_url": "https://mallard-marketplace.vnsf.xyz/archives/net.mallard.discworld-grouping/0.1.0/discworld-grouping.mallardx.minisig",
          "manifest_url": "https://mallard-marketplace.vnsf.xyz/archives/net.mallard.discworld-grouping/0.1.0/plugin.toml",
          "minimum_app_version": "0.0.1",
          "permissions_summary": {
            "sends": true,
            "gmcp_access": [],
            "notifications": false,
            "keychain": false,
            "network": [],
            "filesystem": [],
            "clipboard": "none",
            "external_app": []
          },
          "withdrawn": false,
          "withdrawn_reason": null
        }
      ]
    },
    {
      "id": "net.mallard.discworld-magic",
      "name": "Discworld Magic",
      "description": "",
      "language": "lua",
      "homepage": "https://github.com/wizardquack/mallardx-discworld-magic",
      "tags": [
        "discworld",
        "highlights",
        "magic"
      ],
      "worlds_match": [
        "discworld.starturtle.net:*"
      ],
      "versions": [
        {
          "version": "0.4.1",
          "published_at": "2026-06-04T15:03:58.907Z",
          "archive_url": "https://mallard-marketplace.vnsf.xyz/archives/net.mallard.discworld-magic/0.4.1/discworld-magic.mallardx",
          "archive_sha256": "b5526a82d911ab6c5a0a79425cc98596c17de4f7f56d4b76a456dd77a01e75e4",
          "signature_url": "https://mallard-marketplace.vnsf.xyz/archives/net.mallard.discworld-magic/0.4.1/discworld-magic.mallardx.minisig",
          "manifest_url": "https://mallard-marketplace.vnsf.xyz/archives/net.mallard.discworld-magic/0.4.1/plugin.toml",
          "minimum_app_version": "0.0.1",
          "permissions_summary": {
            "sends": true,
            "gmcp_access": [],
            "notifications": true,
            "keychain": false,
            "network": [],
            "filesystem": [],
            "clipboard": "none",
            "external_app": []
          },
          "withdrawn": false,
          "withdrawn_reason": null
        },
        {
          "version": "0.4.0",
          "published_at": "2026-06-04T15:03:58.357Z",
          "archive_url": "https://mallard-marketplace.vnsf.xyz/archives/net.mallard.discworld-magic/0.4.0/discworld-magic.mallardx",
          "archive_sha256": "ca41e15475182db72f565309c551fb3b6f6dbbe8f7a573026a186746a245c47f",
          "signature_url": "https://mallard-marketplace.vnsf.xyz/archives/net.mallard.discworld-magic/0.4.0/discworld-magic.mallardx.minisig",
          "manifest_url": "https://mallard-marketplace.vnsf.xyz/archives/net.mallard.discworld-magic/0.4.0/plugin.toml",
          "minimum_app_version": "0.0.1",
          "permissions_summary": {
            "sends": true,
            "gmcp_access": [],
            "notifications": true,
            "keychain": false,
            "network": [],
            "filesystem": [],
            "clipboard": "none",
            "external_app": []
          },
          "withdrawn": false,
          "withdrawn_reason": null
        }
      ]
    },
    {
      "id": "net.mallard.discworld-mapper",
      "name": "Discworld Mapper",
      "description": "",
      "language": "lua",
      "homepage": "https://github.com/wizardquack/mallardx-discworld-mapper",
      "tags": [
        "discworld",
        "mapper",
        "panel"
      ],
      "worlds_match": [
        "discworld.starturtle.net:*"
      ],
      "versions": [
        {
          "version": "0.1.2",
          "published_at": "2026-06-04T15:03:53.866Z",
          "archive_url": "https://mallard-marketplace.vnsf.xyz/archives/net.mallard.discworld-mapper/0.1.2/discworld-mapper.mallardx",
          "archive_sha256": "2871a45c5dd1770fedefeb4d115e084aff0fb342229442fd6a4bfec37f412695",
          "signature_url": "https://mallard-marketplace.vnsf.xyz/archives/net.mallard.discworld-mapper/0.1.2/discworld-mapper.mallardx.minisig",
          "manifest_url": "https://mallard-marketplace.vnsf.xyz/archives/net.mallard.discworld-mapper/0.1.2/plugin.toml",
          "minimum_app_version": "0.0.1",
          "permissions_summary": {
            "sends": false,
            "gmcp_access": [
              "char.info",
              "room.info"
            ],
            "notifications": false,
            "keychain": false,
            "network": [],
            "filesystem": [],
            "clipboard": "none",
            "external_app": []
          },
          "withdrawn": false,
          "withdrawn_reason": null
        },
        {
          "version": "0.1.1",
          "published_at": "2026-06-04T15:03:54.861Z",
          "archive_url": "https://mallard-marketplace.vnsf.xyz/archives/net.mallard.discworld-mapper/0.1.1/discworld-mapper.mallardx",
          "archive_sha256": "98027cecdbf7567d69122e417c6e43764dd2e38e39ac6b7ab1e8fba1a4ddd4d3",
          "signature_url": "https://mallard-marketplace.vnsf.xyz/archives/net.mallard.discworld-mapper/0.1.1/discworld-mapper.mallardx.minisig",
          "manifest_url": "https://mallard-marketplace.vnsf.xyz/archives/net.mallard.discworld-mapper/0.1.1/plugin.toml",
          "minimum_app_version": "0.0.1",
          "permissions_summary": {
            "sends": false,
            "gmcp_access": [
              "char.info",
              "room.info"
            ],
            "notifications": false,
            "keychain": false,
            "network": [],
            "filesystem": [],
            "clipboard": "none",
            "external_app": []
          },
          "withdrawn": false,
          "withdrawn_reason": null
        }
      ]
    },
    {
      "id": "net.mallard.discworld-misc",
      "name": "Discworld Misc",
      "description": "",
      "language": "lua",
      "homepage": "https://github.com/wizardquack/mallardx-discworld-misc",
      "tags": [
        "discworld",
        "highlights"
      ],
      "worlds_match": [
        "discworld.starturtle.net:*"
      ],
      "versions": [
        {
          "version": "0.3.2",
          "published_at": "2026-06-04T15:04:01.612Z",
          "archive_url": "https://mallard-marketplace.vnsf.xyz/archives/net.mallard.discworld-misc/0.3.2/discworld-misc.mallardx",
          "archive_sha256": "ad3cd4ccc151c0dc78faee98697b87e1cdc33ddd8443f19659bd2dfd8f4ec4bb",
          "signature_url": "https://mallard-marketplace.vnsf.xyz/archives/net.mallard.discworld-misc/0.3.2/discworld-misc.mallardx.minisig",
          "manifest_url": "https://mallard-marketplace.vnsf.xyz/archives/net.mallard.discworld-misc/0.3.2/plugin.toml",
          "minimum_app_version": "0.0.1",
          "permissions_summary": {
            "sends": false,
            "gmcp_access": [],
            "notifications": false,
            "keychain": false,
            "network": [],
            "filesystem": [],
            "clipboard": "none",
            "external_app": []
          },
          "withdrawn": false,
          "withdrawn_reason": null
        },
        {
          "version": "0.3.1",
          "published_at": "2026-06-04T15:04:01.055Z",
          "archive_url": "https://mallard-marketplace.vnsf.xyz/archives/net.mallard.discworld-misc/0.3.1/discworld-misc.mallardx",
          "archive_sha256": "d811e810643991029c3d3f0a6c8762bf8d13cb7b741d8c25987dab8be02b3b79",
          "signature_url": "https://mallard-marketplace.vnsf.xyz/archives/net.mallard.discworld-misc/0.3.1/discworld-misc.mallardx.minisig",
          "manifest_url": "https://mallard-marketplace.vnsf.xyz/archives/net.mallard.discworld-misc/0.3.1/plugin.toml",
          "minimum_app_version": "0.0.1",
          "permissions_summary": {
            "sends": false,
            "gmcp_access": [],
            "notifications": false,
            "keychain": false,
            "network": [],
            "filesystem": [],
            "clipboard": "none",
            "external_app": []
          },
          "withdrawn": false,
          "withdrawn_reason": null
        },
        {
          "version": "0.3.0",
          "published_at": "2026-06-04T15:04:00.512Z",
          "archive_url": "https://mallard-marketplace.vnsf.xyz/archives/net.mallard.discworld-misc/0.3.0/discworld-misc.mallardx",
          "archive_sha256": "a2365e7d721fbe08c1a744c951138585dd243e39817db8d7f92ceb73379fbccf",
          "signature_url": "https://mallard-marketplace.vnsf.xyz/archives/net.mallard.discworld-misc/0.3.0/discworld-misc.mallardx.minisig",
          "manifest_url": "https://mallard-marketplace.vnsf.xyz/archives/net.mallard.discworld-misc/0.3.0/plugin.toml",
          "minimum_app_version": "0.0.1",
          "permissions_summary": {
            "sends": false,
            "gmcp_access": [],
            "notifications": false,
            "keychain": false,
            "network": [],
            "filesystem": [],
            "clipboard": "none",
            "external_app": []
          },
          "withdrawn": false,
          "withdrawn_reason": null
        }
      ]
    },
    {
      "id": "net.mallard.discworld-sailing",
      "name": "Discworld Sailing",
      "description": "",
      "language": "lua",
      "homepage": "https://github.com/wizardquack/mallardx-discworld-sailing",
      "tags": [
        "discworld",
        "panel",
        "sailing"
      ],
      "worlds_match": [
        "discworld.starturtle.net:*"
      ],
      "versions": [
        {
          "version": "0.5.1",
          "published_at": "2026-06-04T15:04:03.288Z",
          "archive_url": "https://mallard-marketplace.vnsf.xyz/archives/net.mallard.discworld-sailing/0.5.1/discworld-sailing.mallardx",
          "archive_sha256": "f11165c3c3c1496fb991c63c62a81dbac588806341752445b149bd6fdec41dc6",
          "signature_url": "https://mallard-marketplace.vnsf.xyz/archives/net.mallard.discworld-sailing/0.5.1/discworld-sailing.mallardx.minisig",
          "manifest_url": "https://mallard-marketplace.vnsf.xyz/archives/net.mallard.discworld-sailing/0.5.1/plugin.toml",
          "minimum_app_version": "0.0.1",
          "permissions_summary": {
            "sends": false,
            "gmcp_access": [],
            "notifications": false,
            "keychain": false,
            "network": [],
            "filesystem": [],
            "clipboard": "none",
            "external_app": []
          },
          "withdrawn": false,
          "withdrawn_reason": null
        },
        {
          "version": "0.5.0",
          "published_at": "2026-06-04T15:04:03.925Z",
          "archive_url": "https://mallard-marketplace.vnsf.xyz/archives/net.mallard.discworld-sailing/0.5.0/discworld-sailing.mallardx",
          "archive_sha256": "0f432fde511c92e482413bd6bd0bcc4225ed9453551a8fc88edbf1229b303ba4",
          "signature_url": "https://mallard-marketplace.vnsf.xyz/archives/net.mallard.discworld-sailing/0.5.0/discworld-sailing.mallardx.minisig",
          "manifest_url": "https://mallard-marketplace.vnsf.xyz/archives/net.mallard.discworld-sailing/0.5.0/plugin.toml",
          "minimum_app_version": "0.0.1",
          "permissions_summary": {
            "sends": false,
            "gmcp_access": [],
            "notifications": false,
            "keychain": false,
            "network": [],
            "filesystem": [],
            "clipboard": "none",
            "external_app": []
          },
          "withdrawn": false,
          "withdrawn_reason": null
        }
      ]
    },
    {
      "id": "net.mallard.discworld-vitals",
      "name": "Discworld Vitals",
      "description": "",
      "language": "lua",
      "homepage": "https://github.com/wizardquack/mallardx-discworld-vitals",
      "tags": [
        "discworld",
        "panel",
        "vitals"
      ],
      "worlds_match": [
        "discworld.starturtle.net:*"
      ],
      "versions": [
        {
          "version": "0.4.2",
          "published_at": "2026-06-04T15:03:57.880Z",
          "archive_url": "https://mallard-marketplace.vnsf.xyz/archives/net.mallard.discworld-vitals/0.4.2/discworld-vitals.mallardx",
          "archive_sha256": "53347b64647157a307e2fde8300f383d4ad266c74d728245c3de377edd7737df",
          "signature_url": "https://mallard-marketplace.vnsf.xyz/archives/net.mallard.discworld-vitals/0.4.2/discworld-vitals.mallardx.minisig",
          "manifest_url": "https://mallard-marketplace.vnsf.xyz/archives/net.mallard.discworld-vitals/0.4.2/plugin.toml",
          "minimum_app_version": "0.0.1",
          "permissions_summary": {
            "sends": false,
            "gmcp_access": [
              "char.vitals",
              "char.info",
              "char.info.*"
            ],
            "notifications": false,
            "keychain": false,
            "network": [],
            "filesystem": [],
            "clipboard": "none",
            "external_app": []
          },
          "withdrawn": false,
          "withdrawn_reason": null
        },
        {
          "version": "0.4.1",
          "published_at": "2026-06-04T15:03:57.420Z",
          "archive_url": "https://mallard-marketplace.vnsf.xyz/archives/net.mallard.discworld-vitals/0.4.1/discworld-vitals.mallardx",
          "archive_sha256": "8a2d5f34ed29d7ed2633042a0af442a4cc63aa0525b5e03c3f975eccd197f550",
          "signature_url": "https://mallard-marketplace.vnsf.xyz/archives/net.mallard.discworld-vitals/0.4.1/discworld-vitals.mallardx.minisig",
          "manifest_url": "https://mallard-marketplace.vnsf.xyz/archives/net.mallard.discworld-vitals/0.4.1/plugin.toml",
          "minimum_app_version": "0.0.1",
          "permissions_summary": {
            "sends": false,
            "gmcp_access": [
              "char.vitals",
              "char.info",
              "char.info.*"
            ],
            "notifications": false,
            "keychain": false,
            "network": [],
            "filesystem": [],
            "clipboard": "none",
            "external_app": []
          },
          "withdrawn": false,
          "withdrawn_reason": null
        }
      ]
    }
  ]
}
